[
  {
    "id": 0,
    "name": "Michelle Ma",
    "bio": "APM @ Yahoo. Passionate about all things mental/health & wellness. Co-creator of APM Map",
    "image": "https://storage.cloud.google.com/mentors-pics/mima-profile-pic.jpg?authuser=2&organizationId=819335046878",
    "added": "2020-07-12",
    "recommendations": ["4", "86", "76"]
  },
  {
    "id": 1,
    "name": "Some Other Person",
    "bio": "Lorem ipsum dolor sit amet, consectetur adipiscing elit, sed do eiusmod tempor incididunt.",
    "image": "https://source.unsplash.com/random/200x200",
    "added": "2020-07-12",
    "recommendations": []
  }
]
